<?xml version="1.0" encoding="utf-8"?>
<NineGridDictionary>
  <ColorTable />
  <Items>
    <NineGridPathList xmlns:xsi="http://www.w3.org/2001/XMLSchema-instance" xmlns:xsd="http://www.w3.org/2001/XMLSchema">
      <Paths>
        <NineGridPath X="0" Y="0" Color="NodeForeground100" Data="M 2.9729,7.48992L 26.9911,7.48992L 26.9911,22.4524L 2.9729,22.4524L 2.9729,7.48992 Z M 14.787,16.2877C 14.787,15.8761 14.6825,15.5559 14.4735,15.3271C 14.2644,15.0983 13.9537,14.9271 13.5412,14.8135L 12.7951,14.6558L 12.1166,14.5247C 11.8153,14.4522 11.6051,14.3479 11.4859,14.2118C 11.3666,14.0756 11.307,13.888 11.307,13.6487C 11.307,13.3692 11.4267,13.1406 11.6659,12.963C 11.9052,12.7853 12.2221,12.6965 12.6169,12.6965C 12.9762,12.6965 13.3276,12.7626 13.6711,12.8947C 14.0147,13.0268 14.292,13.1928 14.5031,13.3925L 14.555,13.3925L 14.555,12.4827L 13.6899,12.1945L 12.6169,12.0779C 12.0135,12.0779 11.5155,12.2317 11.1228,12.5394C 10.7301,12.8472 10.5337,13.2415 10.5337,13.7224C 10.5337,14.1421 10.6525,14.4825 10.8902,14.7435C 11.1278,15.0045 11.4927,15.1889 11.9849,15.2969L 12.6761,15.4243L 13.2827,15.5518C 13.5292,15.6187 13.7126,15.7125 13.8331,15.8334C 13.9535,15.9542 14.0137,16.1419 14.0137,16.3965C 14.0137,16.705 13.8874,16.9517 13.6349,17.1366C 13.3824,17.3214 13.0297,17.4139 12.577,17.4139C 12.2564,17.4139 11.9138,17.3468 11.5493,17.2127C 11.1848,17.0786 10.8636,16.8878 10.5857,16.6405L 10.5337,16.6405L 10.5337,17.5806L 11.5028,17.919L 12.5746,18.0325C 12.9451,18.0325 13.2621,17.9862 13.5255,17.8936C 13.789,17.8009 14.0193,17.6725 14.2167,17.5081C 14.3972,17.3559 14.5373,17.1704 14.6372,16.9517C 14.7371,16.733 14.787,16.5116 14.787,16.2877 Z M 20.1438,17.8701L 20.1438,17.1741L 17.2825,17.1741L 17.2825,15.1634L 20.1438,15.1634L 20.1438,14.4674L 17.2825,14.4674L 17.2825,12.9207L 20.1438,12.9207L 20.1438,12.2247L 16.5092,12.2247L 16.5092,17.8701L 20.1438,17.8701 Z M 9.34029,18.0282L 7.28854,12.3828L 6.28804,12.3828L 4.23629,18.0282L 5.05916,18.0282L 5.62829,16.4042L 7.94829,16.4042L 8.51741,18.0282L 9.34029,18.0282 Z M 7.72233,15.7855L 5.85062,15.7855L 6.78829,13.1598L 7.72233,15.7855 Z M 25.5838,17.444L 25.5838,16.5643L 25.5307,16.5643C 25.2576,16.8221 24.9646,17.0154 24.6516,17.1443C 24.3387,17.2732 24.0029,17.3376 23.6445,17.3376C 23.3843,17.3376 23.137,17.2913 22.9026,17.1987C 22.6681,17.106 22.4635,16.9626 22.2887,16.7685C 22.1204,16.5832 21.983,16.343 21.8767,16.0477C 21.7703,15.7525 21.7172,15.3995 21.7172,14.9886C 21.7172,14.5963 21.7653,14.2505 21.8616,13.9513C 21.9578,13.652 22.0926,13.4045 22.2658,13.2087C 22.4438,13.0074 22.6462,12.8589 22.8729,12.7635C 23.0997,12.668 23.3545,12.6203 23.6372,12.6203C 23.9828,12.6203 24.3072,12.6817 24.6105,12.8046C 24.9138,12.9274 25.2193,13.1238 25.5271,13.3936L 25.5838,13.3936L 25.5838,12.4995L 24.5864,12.1122L 23.6868,12.0016C 23.2759,12.0016 22.902,12.0673 22.5648,12.1986C 22.2277,12.3299 21.9403,12.5204 21.7027,12.7701C 21.457,13.0271 21.2691,13.3421 21.139,13.715C 21.0089,14.088 20.9438,14.5113 20.9438,14.985C 20.9438,15.4836 21.0115,15.9215 21.1468,16.2985C 21.2822,16.6755 21.4699,16.9864 21.7099,17.2313C 21.9556,17.4802 22.2444,17.6633 22.5763,17.7805C 22.9082,17.8977 23.2771,17.9563 23.6831,17.9563L 24.2746,17.9049L 24.7718,17.7823L 25.2099,17.6149L 25.5838,17.444 Z " />
      </Paths>
    </NineGridPathList>
  </Items>
</NineGridDictionary>
<!-- ORIGINAL XAML SNIPPET
<Canvas xmlns="http://schemas.microsoft.com/winfx/2006/xaml/presentation" xmlns:x="http://schemas.microsoft.com/winfx/2006/xaml" x:Name="InverseSecant__64" Width="30" Height="30" Clip="F1 M 0,0L 30,0L 30,30L 0,30L 0,0">
	<Path x:Name="Shape_2" Width="24.0182" Height="14.9624" Canvas.Left="2.9729" Canvas.Top="7.48992" Stretch="Fill" Fill="#FF5A5A5A" Data="M 2.9729,7.48992L 26.9911,7.48992L 26.9911,22.4524L 2.9729,22.4524L 2.9729,7.48992 Z M 14.787,16.2877C 14.787,15.8761 14.6825,15.5559 14.4735,15.3271C 14.2644,15.0983 13.9537,14.9271 13.5412,14.8135L 12.7951,14.6558L 12.1166,14.5247C 11.8153,14.4522 11.6051,14.3479 11.4859,14.2118C 11.3666,14.0756 11.307,13.888 11.307,13.6487C 11.307,13.3692 11.4267,13.1406 11.6659,12.963C 11.9052,12.7853 12.2221,12.6965 12.6169,12.6965C 12.9762,12.6965 13.3276,12.7626 13.6711,12.8947C 14.0147,13.0268 14.292,13.1928 14.5031,13.3925L 14.555,13.3925L 14.555,12.4827L 13.6899,12.1945L 12.6169,12.0779C 12.0135,12.0779 11.5155,12.2317 11.1228,12.5394C 10.7301,12.8472 10.5337,13.2415 10.5337,13.7224C 10.5337,14.1421 10.6525,14.4825 10.8902,14.7435C 11.1278,15.0045 11.4927,15.1889 11.9849,15.2969L 12.6761,15.4243L 13.2827,15.5518C 13.5292,15.6187 13.7126,15.7125 13.8331,15.8334C 13.9535,15.9542 14.0137,16.1419 14.0137,16.3965C 14.0137,16.705 13.8874,16.9517 13.6349,17.1366C 13.3824,17.3214 13.0297,17.4139 12.577,17.4139C 12.2564,17.4139 11.9138,17.3468 11.5493,17.2127C 11.1848,17.0786 10.8636,16.8878 10.5857,16.6405L 10.5337,16.6405L 10.5337,17.5806L 11.5028,17.919L 12.5746,18.0325C 12.9451,18.0325 13.2621,17.9862 13.5255,17.8936C 13.789,17.8009 14.0193,17.6725 14.2167,17.5081C 14.3972,17.3559 14.5373,17.1704 14.6372,16.9517C 14.7371,16.733 14.787,16.5116 14.787,16.2877 Z M 20.1438,17.8701L 20.1438,17.1741L 17.2825,17.1741L 17.2825,15.1634L 20.1438,15.1634L 20.1438,14.4674L 17.2825,14.4674L 17.2825,12.9207L 20.1438,12.9207L 20.1438,12.2247L 16.5092,12.2247L 16.5092,17.8701L 20.1438,17.8701 Z M 9.34029,18.0282L 7.28854,12.3828L 6.28804,12.3828L 4.23629,18.0282L 5.05916,18.0282L 5.62829,16.4042L 7.94829,16.4042L 8.51741,18.0282L 9.34029,18.0282 Z M 7.72233,15.7855L 5.85062,15.7855L 6.78829,13.1598L 7.72233,15.7855 Z M 25.5838,17.444L 25.5838,16.5643L 25.5307,16.5643C 25.2576,16.8221 24.9646,17.0154 24.6516,17.1443C 24.3387,17.2732 24.0029,17.3376 23.6445,17.3376C 23.3843,17.3376 23.137,17.2913 22.9026,17.1987C 22.6681,17.106 22.4635,16.9626 22.2887,16.7685C 22.1204,16.5832 21.983,16.343 21.8767,16.0477C 21.7703,15.7525 21.7172,15.3995 21.7172,14.9886C 21.7172,14.5963 21.7653,14.2505 21.8616,13.9513C 21.9578,13.652 22.0926,13.4045 22.2658,13.2087C 22.4438,13.0074 22.6462,12.8589 22.8729,12.7635C 23.0997,12.668 23.3545,12.6203 23.6372,12.6203C 23.9828,12.6203 24.3072,12.6817 24.6105,12.8046C 24.9138,12.9274 25.2193,13.1238 25.5271,13.3936L 25.5838,13.3936L 25.5838,12.4995L 24.5864,12.1122L 23.6868,12.0016C 23.2759,12.0016 22.902,12.0673 22.5648,12.1986C 22.2277,12.3299 21.9403,12.5204 21.7027,12.7701C 21.457,13.0271 21.2691,13.3421 21.139,13.715C 21.0089,14.088 20.9438,14.5113 20.9438,14.985C 20.9438,15.4836 21.0115,15.9215 21.1468,16.2985C 21.2822,16.6755 21.4699,16.9864 21.7099,17.2313C 21.9556,17.4802 22.2444,17.6633 22.5763,17.7805C 22.9082,17.8977 23.2771,17.9563 23.6831,17.9563L 24.2746,17.9049L 24.7718,17.7823L 25.2099,17.6149L 25.5838,17.444 Z "/>
</Canvas>
-->