<?xml version="1.0" encoding="utf-8"?>
<NineGridDictionary>
  <ColorTable />
  <Items>
    <NineGridPathList xmlns:xsi="http://www.w3.org/2001/XMLSchema-instance" xmlns:xsd="http://www.w3.org/2001/XMLSchema">
      <Paths>
        <NineGridPath Width="40" Height="40" Color="#b2010101" Data="F1 M11.063,11.708h3.875l-0.5-5.853L11.063,11.708 M3.271,15.188l1.063-1.063   c0.48,0.771,1.125,1.145,1.937,1.145c0.751,0,1.48-0.312,2.147-0.957c0.667-0.625,1.479-1.772,2.437-3.396l3.375-5.813   C13.647,5.041,13.167,5,12.751,5c-1.084,0-1.937,0.292-2.521,0.833C9.647,6.375,9.355,7.167,9.355,8.167L7.813,8.917   c0.104-0.98,0.375-1.792,0.833-2.437c0.479-0.709,1.061-1.209,1.728-1.521c0.667-0.292,1.647-0.5,2.939-0.584   c0.249,0,0.624-0.041,1.167-0.083L16.063,4l0.104,2.604L16.625,12c0.083,1.251,0.229,2.084,0.437,2.48   c0.188,0.416,0.521,0.604,1.021,0.604c0.083,0,0.396,0,0.916-0.043l-0.104,0.5l-3.583,0.605L15,12.292h-4.271   c-0.833,1.437-1.604,2.437-2.333,3c-0.749,0.563-1.625,0.855-2.625,0.855C4.813,16.147,3.98,15.833,3.271,15.188z M34,7H21V5h13V7z    M34,10H21V8h13V10z M34,13H21v-2h13V13z M27,16h-6v-2h6V16z M30,23l2.5-4l2.5,4l-2-1c0,0,1,7-7,7v-1c7,0,6-6,6-6L30,23z M9,25   l4,2.5L9,30l1-2c0,0-7,1-7-7h1c0,7,6,6,6,6L9,25z" />
        <NineGridPath Width="40" Height="40" Color="#FFA99C5E" Data="F1 M20,29.589c0,0.892-0.207,1.552-0.618,1.982s-1.012,0.645-1.8,0.645   c-0.813,0-1.424-0.217-1.834-0.653c-0.41-0.435-0.615-1.085-0.615-1.952c0-0.884,0.21-1.541,0.629-1.969   C16.181,27.214,16.787,27,17.582,27c0.803,0,1.406,0.214,1.811,0.642C19.797,28.07,20,28.719,20,29.589z M18.415,29.603   c0-0.574-0.066-0.961-0.198-1.163c-0.133-0.201-0.35-0.301-0.65-0.301s-0.518,0.101-0.65,0.301   c-0.132,0.201-0.198,0.59-0.198,1.167c0,0.578,0.066,0.967,0.198,1.168c0.133,0.201,0.35,0.301,0.65,0.301s0.518-0.101,0.65-0.301   C18.349,30.574,18.415,30.184,18.415,29.603z M24.074,27.002L19.883,37h-1.443l4.191-9.998H24.074z M27,34.374   c0,0.892-0.206,1.552-0.618,1.982C25.971,36.785,25.37,37,24.583,37c-0.813,0-1.424-0.217-1.834-0.653   c-0.41-0.435-0.615-1.085-0.615-1.952c0-0.884,0.209-1.541,0.629-1.969c0.418-0.428,1.025-0.642,1.82-0.642   c0.803,0,1.405,0.214,1.811,0.642C26.798,32.854,27,33.503,27,34.374z M25.415,34.387c0-0.574-0.066-0.961-0.198-1.163   c-0.132-0.201-0.349-0.301-0.649-0.301s-0.518,0.101-0.65,0.301c-0.133,0.201-0.199,0.59-0.199,1.167   c0,0.578,0.066,0.967,0.199,1.168c0.133,0.201,0.35,0.301,0.65,0.301s0.518-0.101,0.649-0.301   C25.349,35.359,25.415,34.968,25.415,34.387z M28,16h6v-2h-6V16z" />
      </Paths>
    </NineGridPathList>
  </Items>
</NineGridDictionary>
<!-- ORIGINAL XAML SNIPPET
<Canvas xmlns="http://schemas.microsoft.com/winfx/2006/xaml/presentation" xmlns:x="http://schemas.microsoft.com/winfx/2006/xaml" x:Name="FormatIntoString" Width="40" Height="40" Clip="F1 M 0,0L 40,0L 40,40L 0,40L 0,0">
	<Path Fill="#67595959" Width="24.0043" Height="15.2045" Canvas.Left="8" Canvas.Top="3" Stretch="Fill" Data="M 7.38406,13.9451L 8.44314,12.886C 8.92084,13.6543 9.56456,14.0282 10.3745,14.0282C 11.1221,14.0282 11.8489,13.7166 12.5135,13.0729C 13.178,12.4499 13.7854,11.2922 18.1049,3.87842L 16.833,3.79013C 15.753,3.79013 14.9016,4.08086 14.3202,4.62082C 13.7387,5.16073 13.4479,5.94987 13.4479,6.9467L 11.9112,7.6943C 12.0151,6.71827 12.285,5.90833 12.7419,5.26457C 13.2195,4.55852 13.801,4.0601 14.4655,3.74862C 15.1301,3.45789 16.1061,3.25021 17.3937,3.16712L 18.5254,3.05294L 20.1349,2.79334L 20.2387,5.38916L 20.6956,10.7678C 20.7786,12.0138 20.8876,12.7822 21.0953,13.1767C 21.2823,13.5921 21.6144,13.779 22.1129,13.779L 23.0266,13.7374L 22.9592,14.2981L 19.3872,14.9004L 19.0757,11.0585L 14.8185,11.0585C 13.9879,12.4914 13.2195,13.4882 12.4927,14.0489C 11.7451,14.6096 10.8729,14.9004 9.87608,14.9004C 8.92084,14.9004 8.09011,14.5888 7.38406,13.9451 Z M 15.1473,10.4788L 19.01,10.4788L 18.5115,4.64336L 15.1473,10.4788 Z M 24.0051,4.00823L 31.0109,4.00824L 31.0109,5.98734L 24.0051,5.98734L 24.0051,4.00823 Z M 30.9797,9.97692L 23.9738,9.97692L 23.9738,7.97692L 30.9797,7.97692L 30.9797,9.97692 Z M 23.9738,11.9769L 30.9797,11.977L 30.9797,13.9769L 23.9738,13.9769L 23.9738,11.9769 Z M 7.00662,15.9978L 24.0079,15.9978L 24.0079,17.9978L 7.00662,17.9978L 7.00662,15.9978 Z "/>
	<Path Fill="#FF595959" Height="19.853" Canvas.Left="7" Stretch="Fill" Canvas.Top="16.162" Width="24.974" Data="M4.6977099,15.818625 L2.6778319,15.819924 2.3417199,17.84165 4.3616079,17.840349 z M2.0061887,13.820301 L3.0103031,13.820301 2.8425024,14.829314 4.8624104,14.828013 5.0270112,13.838603 6.0311154,13.838603 5.8667148,14.827313 7.0141194,14.826514 6.8500193,15.817225 5.7020147,15.818025 5.3660129,17.839647 6.2611173,17.839048 6.0971158,18.829759 5.2012122,18.830358 5.0312112,19.853071 4.0270069,19.853071 4.1969078,18.830961 2.1769894,18.832262 2.0103589,19.834772 1.0062041,19.834772 1.1727447,18.83296 0,18.833761 0.16409046,17.84305 1.3374053,17.842248&#xd;&#xa;1.6735968,15.820624 0.7531234,15.821225 0.91721386,14.830514 1.8383477,14.829913 z M4.5004104,3.8360004 L7.2101305,8.1988273 5.0287145,6.7672186 5.0287145,11.84615 3.9380065,11.84615 3.9380065,6.7672186 1.7565503,8.1988273 z M17.975691,0 L24.97369,0 24.97369,1.9940004 17.975691,1.9940004 z" />
</Canvas>-->