<?xml version="1.0" encoding="utf-8"?>
<NineGridDictionary>
  <ColorTable />
  <Items>
    <NineGridPathList>
      <Paths>
        <NineGridPath Width="40" Height="40" Color="NodeForeground50" Data="F1 M29,30l-4,2.5l4,2.5l-1-2c0,0,7,1,7-7h-1c0,7-6,6-6,6L29,30z" />
        <NineGridPath Width="40" Height="40" Color="NodeForeground100" Data="F1 M13.792,20.561h3.875l-0.5-5.853L13.792,20.561 M6,24.041l1.063-1.063   c0.48,0.771,1.125,1.145,1.937,1.145c0.751,0,1.48-0.312,2.147-0.957c0.667-0.625,1.479-1.772,2.437-3.396l3.375-5.813   c-0.583-0.063-1.063-0.104-1.479-0.104c-1.084,0-1.937,0.292-2.521,0.833c-0.583,0.541-0.875,1.333-0.875,2.333l-1.541,0.751   c0.104-0.98,0.375-1.792,0.833-2.437c0.479-0.709,1.061-1.209,1.728-1.521c0.667-0.292,1.647-0.5,2.939-0.584   c0.249,0,0.624-0.041,1.167-0.083l1.583-0.292l0.104,2.604l0.459,5.396c0.083,1.251,0.229,2.084,0.437,2.48   c0.188,0.416,0.521,0.604,1.021,0.604c0.083,0,0.396,0,0.916-0.043l-0.104,0.5L18.043,25l-0.313-3.855h-4.271   c-0.833,1.437-1.604,2.437-2.333,3C10.376,24.708,9.5,25,8.5,25C7.543,25,6.709,24.687,6,24.041z M36,17H23v-2h13V17z M36,21H23v-2   h13V21z M36,25H23v-2h13V25z M23.23,30.944l-0.248,1.143h-1.174l-0.349,1.574h1.314l-0.286,1.143h-1.263L20.729,37h-1.27   l0.463-2.196h-1.454L18,37h-1.27l0.451-2.196H16l0.235-1.143h1.193l0.336-1.574h-1.282l0.216-1.143H18l0.47-2.26h1.301l-0.47,2.26   h1.454l0.482-2.26h1.289l-0.47,2.26H23.23z M20.526,32.087h-1.473l-0.349,1.574h1.466L20.526,32.087z M7.412,4.733   c0,0.296-0.043,0.558-0.129,0.785C7.196,5.746,7.074,5.942,6.916,6.11C6.757,6.277,6.567,6.426,6.346,6.559   C6.125,6.69,5.875,6.811,5.597,6.919v1.003H4.05V6.439c0.208-0.056,0.396-0.113,0.564-0.171s0.345-0.154,0.53-0.286   c0.173-0.117,0.308-0.254,0.407-0.409c0.098-0.155,0.147-0.332,0.147-0.528c0-0.293-0.094-0.502-0.284-0.627   C5.226,4.293,4.96,4.23,4.617,4.23c-0.211,0-0.449,0.045-0.714,0.136S3.396,4.575,3.176,4.718H3v-1.34   C3.188,3.299,3.476,3.216,3.866,3.13S4.651,3,5.052,3C5.776,3,6.35,3.16,6.775,3.479C7.2,3.799,7.412,4.217,7.412,4.733z    M5.72,9.68H3.945V8.52H5.72V9.68z M12.962,4.733c0,0.296-0.043,0.558-0.129,0.785c-0.087,0.228-0.209,0.424-0.367,0.592   c-0.158,0.167-0.348,0.316-0.569,0.449c-0.221,0.132-0.471,0.252-0.749,0.36v1.003H9.601V6.439   c0.208-0.056,0.396-0.113,0.564-0.171s0.345-0.154,0.53-0.286c0.173-0.117,0.308-0.254,0.407-0.409   c0.098-0.155,0.147-0.332,0.147-0.528c0-0.293-0.094-0.502-0.284-0.627C10.776,4.293,10.51,4.23,10.167,4.23   c-0.211,0-0.449,0.045-0.714,0.136S8.946,4.575,8.726,4.718H8.55v-1.34C8.738,3.299,9.026,3.216,9.416,3.13S10.201,3,10.603,3   c0.724,0,1.298,0.16,1.723,0.479C12.75,3.799,12.962,4.217,12.962,4.733z M11.271,9.68H9.495V8.52h1.775V9.68z M18.513,4.733   c0,0.296-0.043,0.558-0.129,0.785c-0.087,0.228-0.209,0.424-0.367,0.592c-0.158,0.167-0.348,0.316-0.569,0.449   c-0.221,0.132-0.471,0.252-0.749,0.36v1.003h-1.547V6.439c0.208-0.056,0.396-0.113,0.564-0.171s0.345-0.154,0.53-0.286   c0.173-0.117,0.308-0.254,0.407-0.409c0.098-0.155,0.147-0.332,0.147-0.528c0-0.293-0.094-0.502-0.284-0.627   c-0.188-0.125-0.455-0.187-0.797-0.187c-0.211,0-0.449,0.045-0.714,0.136s-0.507,0.208-0.727,0.352h-0.176v-1.34   c0.188-0.079,0.476-0.162,0.866-0.248S15.751,3,16.153,3c0.724,0,1.298,0.16,1.723,0.479C18.3,3.799,18.513,4.217,18.513,4.733z    M16.821,9.68h-1.775V8.52h1.775V9.68z" />
      </Paths>
    </NineGridPathList>
  </Items>
</NineGridDictionary>