<?xml version="1.0" encoding="utf-8"?>
<NineGridDictionary>
  <ColorTable />
  <Items>
    <NineGridPathList>
      <Paths>
        <NineGridPath Width="40" Height="50" Color="#FFA99C5E" Data="F1 M28.75,13H31v4h-5.719C25.802,13.75,28.75,13,28.75,13z    M27.812,23H31v-4h-5.75C25.25,19,25.812,22,27.812,23z" />
        <NineGridPath Width="40" Height="50" Color="#b2000000" Data="F1 M19,39v-5l-2,1l2.5-4l2.5,4l-2-1v5H19z M35,41H5v2h30V41z M16.492,28.557   c0.802-0.463,6.068-3.504,6.068-3.504l-0.999-1.731c0,0-5.217,3.012-6.068,3.504S15.623,29.058,16.492,28.557z M5.5,18   c-0.957,0-1.791-0.313-2.5-0.959l1.063-1.063c0.48,0.771,1.125,1.145,1.937,1.145c0.751,0,1.48-0.312,2.147-0.957   c0.667-0.625,1.479-1.772,2.437-3.396l3.375-5.813c-0.583-0.063-1.063-0.104-1.479-0.104c-1.084,0-1.937,0.292-2.521,0.833   C9.376,8.228,9.084,9.02,9.084,10.02l-1.541,0.751c0.104-0.98,0.375-1.792,0.833-2.437c0.479-0.709,1.061-1.209,1.728-1.521   c0.667-0.292,1.647-0.5,2.939-0.584c0.249,0,0.624-0.041,1.167-0.083l1.583-0.292l0.104,2.604l0.459,5.396   c0.083,1.251,0.229,2.084,0.437,2.48c0.188,0.416,0.521,0.604,1.021,0.604c0.083,0,0.396,0,0.916-0.043l-0.104,0.5L15.043,18   l-0.313-3.855h-4.271c-0.833,1.437-1.604,2.437-2.333,3C7.376,17.708,6.5,18,5.5,18z M10.792,13.561h3.875l-0.5-5.853   L10.792,13.561z M21.271,22c-0.583-0.583-0.646-2-0.646-2H3v2C3,22,21.25,22.021,21.271,22z M21.062,16H20v2c0,0,0.656,0,0.687,0   C20.844,16.75,21.062,16,21.062,16z M23.375,12H20v2c0,0,1.302,0,1.344,0C22.094,12.646,23.375,12,23.375,12z M37,18.5   c0,4.142-3.358,7.5-7.5,7.5S22,22.642,22,18.5s3.358-7.5,7.5-7.5S37,14.358,37,18.5z M36,18.5c0-3.59-2.91-6.5-6.5-6.5   S23,14.91,23,18.5s2.91,6.5,6.5,6.5S36,22.09,36,18.5z M28,8h-8v2h8V8z" />
      </Paths>
    </NineGridPathList>
  </Items>
</NineGridDictionary>