<?xml version="1.0" encoding="utf-8"?>
<NineGridDictionary>
  <ColorTable />
  <Items>
    <NineGridPathList>
      <Paths>
        <NineGridPath X="0" Y="1" Color="#FFFFFFFF" Data="F1 M 16.7422,0L 16.75,1.25623C 15.9369,1.25629 15.6877,1.91565 15.1042,3.27606C 14.5315,4.65002 14.1298,6.25427 12.4941,6.25427C 10.8584,6.25427 10.4949,4.76044 9.93617,3.40991C 9.41675,2.04169 9.30137,1.25623 8.49606,1.25623C 7.62478,1.25623 7.58862,2.07294 6.99247,3.44775C 6.41675,4.82294 5.95321,6.24188 4.25,6.24188L 4.25,5C 5.03769,5 5.29175,4.22919 5.86979,2.89984C 6.448,1.51044 6.78161,0.00671387 8.49606,0.00671387C 10.1318,0.00671387 10.448,1.44794 11.0105,2.88544C 11.5764,4.29468 11.6888,5.00476 12.4941,5.00476C 13.2994,5.00476 13.4898,4.07123 14.0886,2.66669C 14.6511,1.35419 15.1064,0.0067749 16.7422,0 Z M 0,0L 2,0L 2,1L 1,1L 1,5L 2,5L 2,6L 0,6L 0,0 Z M 21,0L 21,6L 19,6L 19,5L 20,5L 20,1L 19,1L 19,0L 21,0 Z " />
      </Paths>
    </NineGridPathList>
  </Items>
</NineGridDictionary>
<!--Converted from: 

<?xml version="1.0" encoding="utf-8"?>
<Canvas xmlns="http://schemas.microsoft.com/winfx/2006/xaml/presentation" xmlns:x="http://schemas.microsoft.com/winfx/2006/xaml" x:Name="Document" Width="21" Height="6.2543" Clip="F1 M 0,0L 21,0L 21,6.2543L 0,6.2543L 0,0">
	<Canvas x:Name="WaveformGlyph_96" Width="800" Height="600.412" Canvas.Left="0" Canvas.Top="0">
		<Path x:Name="Path" Width="21" Height="6.25427" Canvas.Left="0" Canvas.Top="0" Stretch="Fill" Fill="#FFFFFFFF" Data="F1 M 16.7422,0L 16.75,1.25623C 15.9369,1.25629 15.6877,1.91565 15.1042,3.27606C 14.5315,4.65002 14.1298,6.25427 12.4941,6.25427C 10.8584,6.25427 10.4949,4.76044 9.93617,3.40991C 9.41675,2.04169 9.30137,1.25623 8.49606,1.25623C 7.62478,1.25623 7.58862,2.07294 6.99247,3.44775C 6.41675,4.82294 5.95321,6.24188 4.25,6.24188L 4.25,5C 5.03769,5 5.29175,4.22919 5.86979,2.89984C 6.448,1.51044 6.78161,0.00671387 8.49606,0.00671387C 10.1318,0.00671387 10.448,1.44794 11.0105,2.88544C 11.5764,4.29468 11.6888,5.00476 12.4941,5.00476C 13.2994,5.00476 13.4898,4.07123 14.0886,2.66669C 14.6511,1.35419 15.1064,0.0067749 16.7422,0 Z M 0,0L 2,0L 2,1L 1,1L 1,5L 2,5L 2,6L 0,6L 0,0 Z M 21,0L 21,6L 19,6L 19,5L 20,5L 20,1L 19,1L 19,0L 21,0 Z "/>
	</Canvas>
</Canvas>
-->